_moderngl.py
moderngl/__init__.py
moderngl/mgl.cpython-311-i386-linux-musl.so
moderngl-stubs/__init__.pyi
moderngl.libs/libstdc++-d2a021ba.so.6.0.32
moderngl.libs/libgcc_s-f3fb5a36.so.1
moderngl-5.11.1.dist-info/RECORD
moderngl-5.11.1.dist-info/WHEEL
moderngl-5.11.1.dist-info/LICENSE
moderngl-5.11.1.dist-info/top_level.txt
moderngl-5.11.1.dist-info/METADATA
