Metadata-Version: 2.1
Name: moderngl
Version: 5.11.1
Summary: ModernGL: High performance rendering for Python 3
Home-page: https://github.com/moderngl/moderngl
Author: Szabolcs Dombi
Author-email: szabolcs@szabolcsdombi.com
License: MIT
Project-URL: Documentation, https://moderngl.readthedocs.io/
Project-URL: Source, https://github.com/moderngl/moderngl/
Project-URL: Bug Tracker, https://github.com/moderngl/moderngl/issues/
Keywords: ModernGL,OpenGL,PyOpenGL,rendering,graphics,shader,GLSL,GPU,visualization,2D,3D
Platform: any
Classifier: Development Status :: 5 - Production/Stable
Classifier: License :: OSI Approved
Classifier: License :: OSI Approved :: MIT License
Classifier: Operating System :: OS Independent
Classifier: Topic :: Games/Entertainment
Classifier: Topic :: Multimedia :: Graphics
Classifier: Topic :: Multimedia :: Graphics :: 3D Rendering
Classifier: Topic :: Scientific/Engineering :: Visualization
Classifier: Programming Language :: Python :: 3 :: Only
Requires-Python: >=3.7
License-File: LICENSE
Requires-Dist: glcontext>=3.0.0
Provides-Extra: headless
Requires-Dist: glcontext>=3.0.0; extra == "headless"
